textbook_nvim/__init__.py
textbook_nvim/cli.py
textbook_nvim/parser.py
textbook_nvim/render.py
textbook_nvim-0.5.0.dist-info/entry_points.txt
textbook_nvim-0.5.0.dist-info/LICENSE
textbook_nvim-0.5.0.dist-info/WHEEL
textbook_nvim-0.5.0.dist-info/METADATA
textbook_nvim-0.5.0.dist-info/RECORD
